javar/__init__.py
javar/javar.py
javar/utils.py
javar-0.0.6.dist-info/METADATA
javar-0.0.6.dist-info/WHEEL
javar-0.0.6.dist-info/top_level.txt
javar-0.0.6.dist-info/RECORD
