Metadata-Version: 2.1
Name: javar
Version: 0.0.6
Summary: Javar allows you to generate java cli with a set of options easily.
Home-page: https://github.com/nagolos/javar
Author: Alexander Kulikov
License: MIT
Classifier: Development Status :: 5 - Production/Stable
Classifier: Intended Audience :: Developers
Classifier: License :: OSI Approved :: MIT License
